visreader/__init__.py
visreader/example/__init__.py
visreader/example/imagenet_demo.py
visreader/misc/__init__.py
visreader/misc/edict.py
visreader/misc/filetool.py
visreader/misc/imagetool.py
visreader/misc/kvtool.py
visreader/operators/__init__.py
visreader/operators/base.py
visreader/operators/opencv_ops.py
visreader/operators/pil_ops.py
visreader/pipeline/__init__.py
visreader/pipeline/decorator.py
visreader/pipeline/pipeline.py
visreader/reader_builder/__init__.py
visreader/reader_builder/reader_builder.py
visreader/reader_builder/coco/__init__.py
visreader/reader_builder/coco/box_utils.py
visreader/reader_builder/coco/coco.py
visreader/reader_builder/imagenet/__init__.py
visreader/reader_builder/imagenet/imagenet.py
visreader/shared_queue/__init__.py
visreader/shared_queue/queue.py
visreader/shared_queue/sharedmemory.py
visreader/source/__init__.py
visreader/source/file_reader.py
visreader/source/local_source.py
visreader/source/source.py
visreader/test/__init__.py
visreader/test/seqdata.py
visreader/test/set_env.py
visreader/test/test_coco.py
visreader/test/test_dataset.py
visreader/test/test_imagenet.py
visreader/test/test_operators.py
visreader/test/test_pytransform.py
visreader/test/test_reader_builder.py
visreader/test/test_sharedqueue.py
visreader/transformer/__init__.py
visreader/transformer/libpytransform.so
visreader/transformer/pytransformer.py
visreader-1.0.1.dist-info/DESCRIPTION.rst
visreader-1.0.1.dist-info/METADATA
visreader-1.0.1.dist-info/RECORD
visreader-1.0.1.dist-info/WHEEL
visreader-1.0.1.dist-info/metadata.json
visreader-1.0.1.dist-info/top_level.txt
