Metadata-Version: 2.0
Name: visreader
Version: 1.0.1
Summary: a python tool used in data processing for vision model training
Home-page: https://github.com/PaddlePaddle/VisionTools/tree/master/visreader
Author: wanglong
Author-email: wanglong03@baidu.com
License: UNKNOWN
Platform: UNKNOWN
Requires-Dist: requests (==2.9.2)
Requires-Dist: numpy (>=1.12)
Requires-Dist: scipy (>=0.19.0)
Requires-Dist: Pillow
Requires-Dist: six
Requires-Dist: opencv-python
